<?xml version="1.0" encoding="UTF-8"?>

<!-- generated on 2026-07-21 18:17:56.098568 by Eclipse SUMO osmWebWizard.py v1_27_1+0000-7717f2379d9
<configuration>
    <net-file value="C:\Users\sudha\Sumo\2026-07-21-18-16-49\osm.net.xml.gz"/>
    <ptlines-file value="C:\Users\sudha\Sumo\2026-07-21-18-16-49\osm_ptlines.xml"/>
    <ptstops-file value="C:\Users\sudha\Sumo\2026-07-21-18-16-49\osm_stops.add.xml"/>
    <output-file value="C:\Users\sudha\Sumo\2026-07-21-18-16-49\osm_pt.rou.xml"/>
    <stopinfos-file value="C:\Users\sudha\Sumo\2026-07-21-18-16-49\stopinfos.xml"/>
    <routes-file value="C:\Users\sudha\Sumo\2026-07-21-18-16-49\vehroutes.xml"/>
    <trips-file value="C:\Users\sudha\Sumo\2026-07-21-18-16-49\trips.trips.xml"/>
    <min-stops value="0"/>
    <extend-to-fringe value="True"/>
    <random-begin value="True"/>
    <seed value="42"/>
    <ignore-errors value="True"/>
    <types value="bus,minibus,share_taxi,aerialway"/>
    <vtype-prefix value="pt_"/>
    <verbose value="True"/>
</configuration>
-->

<routes xmlns:xsi="http://www.w3.org/2001/XMLSchema-instance" xsi:noNamespaceSchemaLocation="http://sumo.dlr.de/xsd/routes_file.xsd">
    <vType id="pt_bus" vClass="bus"/>
    <vType id="pt_tram" vClass="tram"/>
    <vType id="pt_train" vClass="rail"/>
    <vType id="pt_subway" vClass="subway"/>
    <vType id="pt_light_rail" vClass="rail_urban"/>
    <vType id="pt_monorail" vClass="rail_urban"/>
    <vType id="pt_trolleybus" vClass="bus"/>
    <vType id="pt_minibus" vClass="bus"/>
    <vType id="pt_share_taxi" vClass="taxi"/>
    <vType id="pt_aerialway" vClass="cable_car" length="2.5" width="2" personCapacity="4"/>
    <vType id="pt_ferry" vClass="ship"/>
    <route id="pt_bus_(-)_OMS:0" edges="566680388#0 566680388#1 566680388#2 566680388#3 566680388#4 586156365#1 586156365#2 586156365#3 44317039 39013518 312031900 37751255#0 37751255#1 584241795#0 584241795#1 657413479 581239050#0 581239050#1 581239050#2 555197196#0 555197196#1 555197196#2 555197196#3 555197196#4 39013523#1 39013523#2 39013523#3 39013523#4 39013523#5 39013523#6 39013523#7 70258965#0 70258965#1 70258965#2 70258965#3 170767287#0 170767287#1 170767287#2 170767287#3 77349489#1 77349489#2 77349489#3 77349489#4 77349489#5 77349489#6 1491586823 70258954#1 70258954#3 70258954#4 70258954#5 555197204 679512999-AddedOnRampEdge 679512999 679512999-AddedOffRampEdge 812684509 631795142 76834907#1 76834908 682971785 76834886#1 682971783 682971782 555197220#0 555197220#1 813012744" >
        <stop busStop="5426388558" duration="20" until="74.0"/> <!-- Nehru Nagar -->
        <stop busStop="6395693844" duration="20" until="174.0"/> <!-- Maharani Bagh -->
        <stop busStop="5121928125" duration="20" until="273.0"/> <!-- Gurudwara Bala Sahib -->
        <stop busStop="5121928128" duration="20" until="378.0"/> <!-- Sarai Kale Khan -->
        <stop busStop="5121928130" duration="20" until="442.0"/> <!-- Sarai Kale Khan ISBT -->
        <stop busStop="6396989742" duration="20" until="676.0"/> <!-- Khel Gaon -->
    </route>
    <route id="pt_bus_(-)_TMS:0" edges="28746245 1457651694 676708027 676708027-AddedOffRampEdge 1451903122 570427347 43359324 565938868#0-AddedOnRampEdge 565938868#0 677074043 1420705472#1 1420705472#2 1420705472#3 1420705472#4 1420705475 565938871#2 565938871#3 565938871#4 565938871#5 565938870 44316345 563679828 44316346" >
        <stop busStop="4819437823" duration="20" until="158.0"/> <!-- Safdarjung Hospital -->
        <stop busStop="5426388566" duration="20" until="310.0"/> <!-- South Extension -->
        <stop busStop="6112155497" duration="20" until="438.0"/> <!-- Andrews Ganj -->
    </route>
    <route id="pt_bus_(-)_TMS:1" edges="566680388#0 566680388#1 566680388#2 566680388#3 566680388#4 586156365#1 586156365#2 586156365#3 44317039 39013518 312031900 37751255#0 37751255#1 584241795#0 584241795#1 657413479 581239050#0 581239050#1 581239050#2 555197196#0 555197196#1 555197196#2 555197196#3 555197196#4 39013523#1 39013523#2 39013523#3 39013523#4 39013523#5 39013523#6 39013523#7 70258965#0 70258965#1 70258965#2 70258965#3 170767287#0 170767287#1 170767287#2 170767287#3 77349489#1 77349489#2 77349489#3 77349489#4 77349489#5 77349489#6 1491586823 70258954#1 70258954#3 70258954#4 70258954#5 555197204 679512999-AddedOnRampEdge 679512999 679512999-AddedOffRampEdge 679512998 679512997 1313465445 70258948#0 70258948#1 70258948#2" >
        <stop busStop="5426388558" duration="20" until="120.0"/> <!-- Nehru Nagar -->
        <stop busStop="5121928122" duration="20" until="253.0"/> <!-- Maharani Bagh -->
        <stop busStop="5121928125" duration="20" until="372.0"/> <!-- Gurudwara Bala Sahib -->
        <stop busStop="5121928128" duration="20" until="477.0"/> <!-- Sarai Kale Khan -->
        <stop busStop="5121928130" duration="20" until="543.0"/> <!-- Sarai Kale Khan ISBT -->
        <stop busStop="6362085192@9297931" duration="20" until="659.0"/> <!-- Indraprastha Park -->
        <stop busStop="6362085189" duration="20" until="719.0"/> <!-- Nizamuddin Road Bridge -->
    </route>
    <route id="pt_bus_166:0" edges="584241789#1 1203083884 1203083883#1 1203083883#3 176466591#1 176466591#2 176466591#3 176466591#4 176466591#5 584241784#0 584241793#0 584241793#4 1090402162 77339656#0 77339656#1 77339656#4 77339656#5 77339656#6 77339656#11 77339656#12 77339656#13 680551215 561759719#0 561759719#1 561759719#2 561759719#3 561759719#4 678397108 678397107#0 678397107#1 561759718#0 561759718#1 561759718#2 561759718#3 561759718#4 561759718#5 585446272#0 585446285#0 585446285#1 585446285#2 585446285#3 585446284#0 176492654#2 176492654#3 176492654#4 176492654#5 176492654#6 176492654#7 176492654#8 176492654#11 176492654#12 176492654#13 176492654#14 176492654#15 176492654#18 176492654#19 1187268491#0 1187268491#1 1187268491#2 1187268490 24577364#0 24577364#1 1077595194 -24577367#8 -24577367#7 -24577367#6 -24577367#4 -24577367#2 -24577367#1 -24577367#0 1077595195#1 732001894 581989172#0 581989172#1 604050032 24577379#0 24577379#1 24577379#2 582461174#0 582461174#1 582461174#2 296963058#0 296963058#1 296963058#2 296963058#3 296963058#4 296963058#5 296963058#6 296963058#7" >
        <stop busStop="938635417" duration="20" until="35.0"/> <!-- Nizamuddin Railway Station -->
        <stop busStop="6371764317" duration="20" until="160.0"/> <!-- Hazarat Nizamuddin -->
        <stop busStop="5273109722" duration="20" until="225.0"/> <!-- DPS School (near Neela Gumbad) -->
        <stop busStop="5426390776" duration="20" until="329.0"/> <!-- ISPAT Bhawan -->
        <stop busStop="5426390921" duration="20" until="417.0"/> <!-- Dayal Singh College -->
        <stop busStop="355435748" duration="20" until="493.0"/> <!-- Sujan Singh Park -->
        <stop busStop="5732544103" duration="20" until="690.0"/> <!-- Shahjahan Road UPSC -->
    </route>
    <route id="pt_bus_166:1" edges="680551206 680551212#0 680551212#1 680551212#2 296963059#0 296963059#1 296963059#2 1126646522#0 24577367#0 24577367#1 24577367#2 24577367#4 24577367#6 24577367#7 24577367#8 1126646523 783084113#1 783084113#2 732001895#0 732001905 1187268486 1187268489#0 1187268489#1 732001908#0 732001908#1 1187268492#1 80958874#0 80958874#1 80958874#2 80958874#5 80958874#6 80958874#7 80958874#8 80958874#9 80958874#10 80958874#11 80958874#12 80958874#13 80958874#14 80958874#15 730290863 24563348#0 24563348#1 24563348#3 24563348#4 24563348#7 24563348#8 24563348#9 24563348#9-AddedOffRampEdge 24563348#10 24563348#11 678397112 678397111#0 678397111#1 678397111#2 680551213 680551205 24563333#0 24563333#1 24563333#2 24563333#3 24563333#4 39013511#0 39013511#1 39013511#2 39013511#3 39013511#6 39013511#7 39013511#8 39013511#9 39013511#10 39013511#13 39013511#14 163778522#0 163778522#1 176466583" >
        <stop busStop="6854465827" duration="20" until="143.0"/> <!-- Humayun Road -->
        <stop busStop="5426389916" duration="20" until="227.0"/> <!-- Sujan Singh Park -->
        <stop busStop="7062645321" duration="20" until="333.0"/> <!-- Bharti Nagar -->
        <stop busStop="5426388555" duration="20" until="400.0"/> <!-- Dayal Singh College -->
        <stop busStop="7062680765" duration="20" until="477.0"/> <!-- Jawaharlal Nehru Stadium -->
        <stop busStop="7062680768" duration="20" until="565.0"/> <!-- ISPAT Bhawan -->
        <stop busStop="7062680766" duration="20" until="661.0"/> <!-- DPS School (near Neela Gumbad) -->
        <stop busStop="6372277578" duration="20" until="732.0"/> <!-- Dargah Hazarat Nizamuddin -->
        <stop busStop="6385492244" duration="20" until="806.0"/> <!-- Hazarat Nizamuddin -->
        <stop busStop="938635590" duration="20" until="928.0"/> <!-- Nizamuddin Railway Station -->
    </route>
    <route id="pt_bus_181A:0" edges="680551206 680551212#0 680551212#1 680551212#2 296963059#0 296963059#1 296963059#2 1126646522#0 24577367#0 24577367#1 24577367#2 24577367#4 24577367#6 24577367#7 24577367#8 1126646523 783084113#1 783084113#2 732001895#0 732001905 1187268486 1187268489#0 1187268489#1 732001908#0 732001908#1 1187268492#1 80958874#0 80958874#1 80958874#2 80958874#5 80958874#6 80958874#7 80958874#8 80958874#9 80958874#10 80958874#11 80958874#12 80958874#13 80958874#14 80958874#15 730290863 24563348#0 24563348#1 24563348#3 24563348#4 24563348#7 24563348#8 24563348#9 24563348#9-AddedOffRampEdge 24563348#10 24563348#11 678397112 678397111#0 678397111#1 678397111#2 680551213 680551205 24563333#0 24563333#1 24563333#2 24563333#3 24563333#4 39013511#0 39013511#1 39013511#2 39013511#3 39013511#6 39013511#7 39013511#8 39013511#9 39013511#10 39013511#13 39013511#14 163778522#0 163778522#1 176466583" >
        <stop busStop="6854465827" duration="20" until="124.0"/> <!-- Humayun Road -->
        <stop busStop="5426389916" duration="20" until="226.0"/> <!-- Sujan Singh Park -->
        <stop busStop="7062645321" duration="20" until="311.0"/> <!-- Bharti Nagar -->
        <stop busStop="5426388555" duration="20" until="379.0"/> <!-- Dayal Singh College -->
        <stop busStop="7062680765" duration="20" until="457.0"/> <!-- Jawaharlal Nehru Stadium -->
        <stop busStop="7062680768" duration="20" until="535.0"/> <!-- ISPAT Bhawan -->
        <stop busStop="7062680766" duration="20" until="615.0"/> <!-- DPS School (near Neela Gumbad) -->
        <stop busStop="6372277578" duration="20" until="683.0"/> <!-- Dargah Hazarat Nizamuddin -->
        <stop busStop="6385492244" duration="20" until="756.0"/> <!-- Hazarat Nizamuddin -->
        <stop busStop="938635590" duration="20" until="863.0"/> <!-- Nizamuddin Railway Station -->
    </route>
    <route id="pt_bus_181A:1" edges="584241789#1 1203083884 1203083883#1 1203083883#3 176466591#1 176466591#2 176466591#3 176466591#4 176466591#5 584241784#0 584241793#0 584241793#4 1090402162 77339656#0 77339656#1 77339656#4 77339656#5 77339656#6 77339656#11 77339656#12 77339656#13 680551215 561759719#0 561759719#1 561759719#2 561759719#3 561759719#4 678397108 678397107#0 678397107#1 561759718#0 561759718#1 561759718#2 561759718#3 561759718#4 561759718#5 585446272#0 585446285#0 585446285#1 585446285#2 585446285#3 585446284#0 176492654#2 176492654#3 176492654#4 176492654#5 176492654#6 176492654#7 176492654#8 176492654#11 176492654#12 176492654#13 176492654#14 176492654#15 176492654#18 176492654#19 1187268491#0 1187268491#1 1187268491#2 1187268490 24577364#0 24577364#1 1077595194 -24577367#8 -24577367#7 -24577367#6 24577367#6 -24577367#6 -24577367#4 -24577367#2 -24577367#1 -24577367#0 1077595195#1 732001894 581989172#0 581989172#1 604050032 24577379#0 24577379#1 24577379#2 582461174#0 582461174#1 582461174#2 296963058#0 296963058#1 296963058#2 296963058#3 296963058#4" >
        <stop busStop="938635417" duration="20" until="36.0"/> <!-- Nizamuddin Railway Station -->
        <stop busStop="6371764317" duration="20" until="190.0"/> <!-- Hazarat Nizamuddin -->
        <stop busStop="5273109722" duration="20" until="255.0"/> <!-- DPS School (near Neela Gumbad) -->
        <stop busStop="5426390776" duration="20" until="331.0"/> <!-- ISPAT Bhawan -->
        <stop busStop="5426390921" duration="20" until="455.0"/> <!-- Dayal Singh College -->
        <stop busStop="7655631102" duration="20" until="522.0"/> <!-- Bharti Nagar -->
        <stop busStop="355435748" duration="20" until="579.0"/> <!-- Sujan Singh Park -->
        <stop busStop="10221267679" duration="20" until="706.0"/> <!-- Humayun Road -->
        <stop busStop="5732544103" duration="20" until="836.0"/> <!-- Shahjahan Road UPSC -->
    </route>
    <route id="pt_bus_311A:0" edges="566680388#0 566680388#1 566680388#2 566680388#3 566680388#4 586156365#1 586156365#2 586156365#3 44317039 39013518 312031900 37751255#0 37751255#1 584241795#0 584241795#1 657413479 581239050#0 581239050#1 581239050#2 555197196#0 555197196#1 555197196#2 555197196#3 555197196#4 39013523#1 39013523#2 39013523#3 39013523#4 39013523#5 39013523#6 39013523#7 70258965#0 70258965#1 70258965#2 70258965#3 170767287#0 170767287#1 170767287#2 170767287#3 77349489#1 77349489#2 77349489#3 77349489#4 77349489#5 77349489#6 1491586823 70258954#1 70258954#3 70258954#4 70258954#5 555197204 679512999-AddedOnRampEdge 679512999 679512999-AddedOffRampEdge 812684509 631795142 76834907#1 76834908 682971785 76834886#1 682971783 682971782 555197220#0 555197220#1 813012744" >
        <stop busStop="6497625779" duration="20" until="58.0"/> <!-- PGDAV College -->
        <stop busStop="5426388558" duration="20" until="118.0"/> <!-- Nehru Nagar -->
        <stop busStop="6395693844" duration="20" until="263.0"/> <!-- Maharani Bagh -->
        <stop busStop="5121928125" duration="20" until="378.0"/> <!-- Gurudwara Bala Sahib -->
        <stop busStop="5121928128" duration="20" until="485.0"/> <!-- Sarai Kale Khan -->
        <stop busStop="5121928130" duration="20" until="549.0"/> <!-- Sarai Kale Khan ISBT -->
        <stop busStop="6396989742" duration="20" until="782.0"/> <!-- Khel Gaon -->
    </route>
    <route id="pt_bus_323:0" edges="28746245 1457651694 676708027 676708027-AddedOffRampEdge 1451903122 570427347 43359324 565938868#0-AddedOnRampEdge 565938868#0 677074043 1420705472#1 1420705472#2 1420705472#3 1420705472#4 1420705475 565938871#2 565938871#3 565938871#4 565938871#5 565938870 44316345 563679828 44316346" >
        <stop busStop="4819437823" duration="20" until="130.0"/> <!-- Safdarjung Hospital -->
        <stop busStop="5426388566" duration="20" until="279.0"/> <!-- South Extension -->
        <stop busStop="6112155497" duration="20" until="409.0"/> <!-- Andrews Ganj -->
    </route>
    <route id="pt_bus_347:0" edges="76834871 211191578 852601469#0 852601469#1 852601469#2 852601468#0 852601468#1 852601468#2" >
        <stop busStop="7242732172" duration="20" until="68.0"/> <!-- Temporary Stop -->
        <stop busStop="6497707582" duration="20" until="129.0"/> <!-- Delhi Police Apartment -->
    </route>
    <route id="pt_bus_405:0" edges="77339656#11 77339656#12 77339656#13 680551215 561759719#0 561759719#1 561759719#2 561759719#3 561759719#4 678397108 678397106 678397105 555242574-AddedOnRampEdge 555242574 77349464#0 77349464#1 77349464#1-AddedOffRampEdge 77349464#2 562479736#0 562479736#1 562479736#3 562479736#4" >
        <stop busStop="6371764317" duration="20" until="85.0"/> <!-- Hazarat Nizamuddin -->
        <stop busStop="5273109722" duration="20" until="150.0"/> <!-- DPS School (near Neela Gumbad) -->
        <stop busStop="5342182750" duration="20" until="255.0"/> <!-- None -->
        <stop busStop="5342182505" duration="20" until="318.0"/> <!-- None -->
    </route>
    <route id="pt_bus_405:1" edges="662141606#0 662141606#4 662141606#4-AddedOffRampEdge 662141606#5 662141606#6 760525681#0 760525681#1 584241794 202645529#0 202645529#1 202645529#2 1312806548 584241793#0 584241793#4 1090402162 77339656#0 77339656#1 77339656#4 77339656#5 77339656#6 77339656#11 77339656#12 77339656#13 680551215 561759719#0 561759719#1 561759719#2 561759719#3 561759719#4 678397108 678397106 678397105 555242574-AddedOnRampEdge 555242574 77349464#0 77349464#1 77349464#1-AddedOffRampEdge 77349464#2 562479736#0 562479736#1 562479736#3 562479736#4" >
        <stop busStop="6198752458" duration="20" until="82.0"/> <!-- New Friends Colony -->
        <stop busStop="910451189" duration="20" until="154.0"/> <!-- Ashram -->
        <stop busStop="6371764317" duration="20" until="369.0"/> <!-- Hazarat Nizamuddin -->
        <stop busStop="5273109722" duration="20" until="433.0"/> <!-- DPS School (near Neela Gumbad) -->
        <stop busStop="5342182750" duration="20" until="551.0"/> <!-- None -->
        <stop busStop="5342182505" duration="20" until="614.0"/> <!-- None -->
    </route>
    <route id="pt_bus_410:0" edges="-653235647#0 -38116089#12 -38116089#11 -38116089#10 -38116089#9 -38116089#8 -38116089#7 -38116090#4 -1076000734 -424007912#2 -424007912#1 -1202758360 -424014386 168275206#0 168275206#1 -424014365#6 -424014365#5 -424014365#4 -424014365#3 1306749688 -38116089#1 652047004 583620105#1 583620105#2 583620105#3 583620105#4 583620105#5 168381546#0 168381546#1 583910216 579507806 583620104#0 -1187796048 -424014401#0 -424014444#4 -424014444#3 -424014444#2 -424014444#1 -424014444#0 38116092#2 1183845653#0 1183845653#1 -168275173#2 -168275173#0 -38116091#1 -38116091#0 -677418645 -677418649 -38116094#9 -38116094#8 -38116094#7 -38116094#6 -38116094#5 -38116094#4 -38116094#3 -38116094#2 -660172544#8 -660172544#7 -660172544#6 -660172544#4 -660172544#3 -660172544#2 -660172544#1 -660172544#0 -1076257529#2 621256677 621256674#1 621256672 621256666#0 621256666#0-AddedOffRampEdge 621256668#0 768102459#2 -186810182#3 -186810182#2 -186810182#1 -186810182#0 205080608#1 205080608#2 205080608#3 205080608#4 205080608#5 -169421699#0 -169421731 1057070263 28153848#0 28153848#1 28153848#2 28153848#3 28153848#4 28153848#5 28153848#6 28153848#7 28153848#8 28153848#9 28153848#10 28153848#11 28153848#12 1186664897#0 77339655#8 77339655#9 730237457#0 730237457#3 1451897494-AddedOnRampEdge 1451897494 1451897494-AddedOffRampEdge 77015779#1 715377036-AddedOnRampEdge 715377036 77349488#1 77349488#2 77349488#3 77349488#4 77349488#5 584241782 37751254#0 37751254#1 37751254#2 760525680 566680381-AddedOnRampEdge 566680381 1313030094 39013521 1313030095 586156360#1 586156360#2 586156360#3 566009660#0 733576742 566680388#4 586156365#1 586156365#2 586156365#3 44317039 39013518 312031900 37751255#0 37751255#1 584241795#0 584241795#1 584241794 202645529#0 202645529#1 202645529#2 1312806548 584241793#0 584241793#4 1090402162 77339656#0 77339656#1 77339656#4 77339656#5 77339656#6 77339656#11 77339656#12 77339656#13 680551215 680551214 680551213 1313158398 570859682#0 570859682#1 570859682#2 570859682#3 570859682#3-AddedOffRampEdge 570859682#4 570859682#6 77349485#1 77349485#2 77349485#3 77349485#4 680551212#0 680551212#1 680551212#2 582461172" >
        <stop busStop="-6122143946" duration="20" until="35.0"/> <!-- Jal Vihar Terminal -->
        <stop busStop="6203988021" duration="20" until="230.0"/> <!-- Lajpat Nagar (DJB) -->
        <stop busStop="5426388558" duration="20" until="821.0"/> <!-- Nehru Nagar -->
        <stop busStop="5584870725" duration="20" until="904.0"/> <!-- Ashram -->
        <stop busStop="6371764317" duration="20" until="1049.0"/> <!-- Hazarat Nizamuddin -->
        <stop busStop="6077096067" duration="20" until="1158.0"/> <!-- Golf Club -->
        <stop busStop="6385537594" duration="20" until="1242.0"/> <!-- Bapa Nagar -->
    </route>
    <route id="pt_bus_410:1" edges="44831985#0 44831985#1 44831985#2 44831985#3 1187268470#0 1187268470#1 1187268470#3 1199333276 1313161443 1199333278 77349527 77349521 697289105-AddedOnRampEdge 697289105 24563333#0 24563333#1 24563333#2 24563333#3 24563333#4 39013511#0 39013511#1 39013511#2 39013511#3 39013511#6 39013511#7 39013511#8 39013511#9 39013511#10 39013511#13 39013511#14 39013511#15 39013511#16 77339658 77339655#0 77339655#1 77339655#3 77339655#4 77339655#8 77339655#9 730237457#0 730237457#3 1451897494-AddedOnRampEdge 1451897494 1451897494-AddedOffRampEdge 77015779#1 715377036-AddedOnRampEdge 715377036 77349488#1 77349488#2 77349488#3 77349488#4 77349488#5 584241782 37751254#0 37751254#1 37751254#2 760525680 566680381-AddedOnRampEdge 566680381 1313030094 39013521 1313030095 586156360#1 586156360#2 586156360#3 566009660#0 733576742 566680388#4 586156365#1 586156365#2 586156365#3 44317039 39013518 312031900 37751255#0 37751255#1 584241795#0 584241795#1 584241794 202645529#0 202645529#1 202645529#2 1312806548 584241793#0 584241793#4 1090402158#0 1090402158#1 1090402158#2 1090402158#3 1090402158#4 1090402158#6 1090402158#8 1090402158#9 1090402158#10 1090402158#11 1090402158#12 1090402158#13 1090402165 1090402167 1090402166 312031903#0 312031903#1 312031903#2 312031903#3 312031903#4 1212071851#3 1212071851#4 1212071851#5 186810178#0 186810178#1 1312784813 169421728 202800232 1312784809 1312784810 202800230#0 202800230#1 -652550331 1149879785 1183838119 652550336#0 652550336#2 652550336#3 652550336#5 652550336#6 652550336#9 652550336#10 652550336#11 652550336#12 652550336#13 652550336#14 652550336#15 652550336#17 652550336#19 652550336#20 652550336#21 652550336#22 652550336#23 652550336#24 652550336#26 652550336#27 38116092#0 38116092#1 424014444#0 424014444#1 424014444#2 424014444#3 424014444#4 424014444#5 583620104#3 583620104#4 583620104#5 583620104#6 583620104#7 38116089#1 -1306749688 424014365#3 424014365#4 424014365#5 424014365#6 -168275206#1 -168275206#0 424014386 1202758360 424007912#1 424007912#2 1076000734 38116090#4 38116089#7 38116089#8 38116089#9 38116089#10 38116089#11 38116089#12 38116089#13" >
        <stop busStop="6385537600" duration="20" until="72.0"/> <!-- Bapa Nagar -->
        <stop busStop="6372277579" duration="20" until="187.0"/> <!-- Golf Club -->
        <stop busStop="6372277578" duration="20" until="293.0"/> <!-- Dargah Hazarat Nizamuddin -->
        <stop busStop="6385492244" duration="20" until="350.0"/> <!-- Hazarat Nizamuddin -->
        <stop busStop="5584872921" duration="20" until="505.0"/> <!-- Ashram -->
        <stop busStop="5426389543" duration="20" until="621.0"/> <!-- Nehru Nagar -->
        <stop busStop="5430723253" duration="20" until="673.0"/> <!-- Sri Niwas Puri -->
        <stop busStop="6372277576" duration="20" until="1186.0"/> <!-- Lajpat Nagar (DJB) -->
        <stop busStop="6122143946" duration="20" until="1390.0"/> <!-- Jal Vihar Terminal -->
    </route>
    <route id="pt_bus_410A:0" edges="44831985#0 44831985#1 44831985#2 44831985#3 1187268470#0 1187268470#1 1187268470#3 1199333276 1313161443 1199333278 77349527 77349521 697289105-AddedOnRampEdge 697289105 24563333#0 24563333#1 24563333#2 24563333#3 24563333#4 39013511#0 39013511#1 39013511#2 39013511#3 39013511#6 39013511#7 39013511#8 39013511#9 39013511#10 39013511#13 39013511#14 39013511#15 39013511#16 77339658 77339655#0 77339655#1 77339655#3 77339655#4 77339655#8 77339655#9 730237457#0 730237457#3 1451897494-AddedOnRampEdge 1451897494 1451897494-AddedOffRampEdge 77015779#1 715377036-AddedOnRampEdge 715377036 77349488#1 77349488#2 77349488#3 77349488#4 77349488#5 584241782 37751254#0 37751254#1 37751254#2 760525680 566680381-AddedOnRampEdge 566680381 1313030094 39013521 1313030095 586156360#1 586156360#2 586156360#3 566009660#0 733576742 566680388#4 586156365#1 586156365#2 586156365#3 44317039 39013518 312031900 37751255#0 37751255#1 584241795#0 584241795#1 584241794 202645529#0 202645529#1 202645529#2 1312806548 584241793#0 584241793#4 1090402158#0 1090402158#1 1090402158#2 1090402158#3 1090402158#4 1090402158#6 1090402158#8 1090402158#9 1090402158#10 1090402158#11 1090402158#12 1090402158#13 1090402165 1090402167 1090402166 312031903#0 312031903#1 312031903#2 312031903#3 312031903#4 1212071851#3 1212071851#4 1212071851#5 186810178#0 186810178#1 1312784813 169421728 202800232 1312784809 1312784810 202800230#0 202800230#1 -652550331 1149879785 1183838119 652550336#0 652550336#2 652550336#3 652550336#5 652550336#6 652550336#9 652550336#10 652550336#11 652550336#12 652550336#13 652550336#14 652550336#15 652550336#17 652550336#19 652550336#20 652550336#21 652550336#22 652550336#23 652550336#24 652550336#26 652550336#27 38116092#0 38116092#1 424014444#0 424014444#1 424014444#2 424014444#3 424014444#4 424014444#5 583620104#3 583620104#4 583620104#5 583620104#6 583620104#7 38116089#1 -1306749688 424014365#3 424014365#4 424014365#5 424014365#6 -168275206#1 -168275206#0 424014386 1202758360 424007912#1 424007912#2 1076000734 38116090#4 38116089#7 38116089#8 38116089#9 38116089#10 38116089#11 38116089#12 38116089#13" >
        <stop busStop="6385537600" duration="20" until="72.0"/> <!-- Bapa Nagar -->
        <stop busStop="6372277579" duration="20" until="142.0"/> <!-- Golf Club -->
        <stop busStop="6372277578" duration="20" until="253.0"/> <!-- Dargah Hazarat Nizamuddin -->
        <stop busStop="6385492244" duration="20" until="308.0"/> <!-- Hazarat Nizamuddin -->
        <stop busStop="5584872921" duration="20" until="474.0"/> <!-- Ashram -->
        <stop busStop="5426389543" duration="20" until="603.0"/> <!-- Nehru Nagar -->
        <stop busStop="5430723253" duration="20" until="657.0"/> <!-- Sri Niwas Puri -->
        <stop busStop="6372277576" duration="20" until="1173.0"/> <!-- Lajpat Nagar (DJB) -->
        <stop busStop="6122143946" duration="20" until="1375.0"/> <!-- Jal Vihar Terminal -->
    </route>
    <route id="pt_bus_410A:1" edges="-653235647#0 -38116089#12 -38116089#11 -38116089#10 -38116089#9 -38116089#8 -38116089#7 -38116090#4 -1076000734 -424007912#2 -424007912#1 -1202758360 -424014386 168275206#0 168275206#1 -424014365#6 -424014365#5 -424014365#4 -424014365#3 1306749688 -38116089#1 652047004 583620105#1 583620105#2 583620105#3 583620105#4 583620105#5 168381546#0 168381546#1 583910216 579507806 583620104#0 -1187796048 -424014401#0 -424014444#4 -424014444#3 -424014444#2 -424014444#1 -424014444#0 38116092#2 1183845653#0 1183845653#1 -168275173#2 -168275173#0 -38116091#1 -38116091#0 -677418645 -677418649 -38116094#9 -38116094#8 -38116094#7 -38116094#6 -38116094#5 -38116094#4 -38116094#3 -38116094#2 -660172544#8 -660172544#7 -660172544#6 -660172544#4 -660172544#3 -660172544#2 -660172544#1 -660172544#0 -1076257529#2 621256677 621256674#1 621256672 621256666#0 621256666#0-AddedOffRampEdge 621256668#0 768102459#2 -186810182#3 -186810182#2 -186810182#1 -186810182#0 205080608#1 205080608#2 205080608#3 205080608#4 205080608#5 -169421699#0 -169421731 1057070263 28153848#0 28153848#1 28153848#2 28153848#3 28153848#4 28153848#5 28153848#6 28153848#7 28153848#8 28153848#9 28153848#10 28153848#11 28153848#12 1186664897#0 77339655#8 77339655#9 730237457#0 730237457#3 1451897494-AddedOnRampEdge 1451897494 1451897494-AddedOffRampEdge 77015779#1 715377036-AddedOnRampEdge 715377036 77349488#1 77349488#2 77349488#3 77349488#4 77349488#5 584241782 37751254#0 37751254#1 37751254#2 760525680 566680381-AddedOnRampEdge 566680381 1313030094 39013521 1313030095 586156360#1 586156360#2 586156360#3 566009660#0 733576742 566680388#4 586156365#1 586156365#2 586156365#3 44317039 39013518 312031900 37751255#0 37751255#1 584241795#0 584241795#1 584241794 202645529#0 202645529#1 202645529#2 1312806548 584241793#0 584241793#4 1090402162 77339656#0 77339656#1 77339656#4 77339656#5 77339656#6 77339656#11 77339656#12 77339656#13 680551215 680551214 680551213 1313158398 570859682#0 570859682#1 570859682#2 570859682#3 570859682#3-AddedOffRampEdge 570859682#4 570859682#6 77349485#1 77349485#2 77349485#3 77349485#4 680551212#0 680551212#1 680551212#2 582461172" >
        <stop busStop="-6122143946" duration="20" until="34.0"/> <!-- Jal Vihar Terminal -->
        <stop busStop="6203988021" duration="20" until="229.0"/> <!-- Lajpat Nagar (DJB) -->
        <stop busStop="5426388558" duration="20" until="832.0"/> <!-- Nehru Nagar -->
        <stop busStop="5584870725" duration="20" until="912.0"/> <!-- Ashram -->
        <stop busStop="6371764317" duration="20" until="1134.0"/> <!-- Hazarat Nizamuddin -->
        <stop busStop="6077096067" duration="20" until="1242.0"/> <!-- Golf Club -->
        <stop busStop="6385537594" duration="20" until="1312.0"/> <!-- Bapa Nagar -->
    </route>
    <route id="pt_bus_413:0" edges="584241789#1 1203083884 1203083883#1 1203083883#3 176466591#1 176466591#2 176466591#3 176466591#4 176466591#5 584241787 1451897494-AddedOnRampEdge 1451897494 1451897494-AddedOffRampEdge 77015779#1 715377036-AddedOnRampEdge 715377036 77349488#1 77349488#2 77349488#3 77349488#4 77349488#5 584241782 37751254#0 37751254#1 37751254#2 760525680 566680381-AddedOnRampEdge 566680381 1313030094 39013521 1313030095 566680382 1313027075" >
        <stop busStop="938635417" duration="20" until="36.0"/> <!-- Nizamuddin Railway Station -->
        <stop busStop="5584872921" duration="20" until="162.0"/> <!-- Ashram -->
        <stop busStop="5585958328" duration="20" until="255.0"/> <!-- Nehru Nagar -->
    </route>
    <route id="pt_bus_413:1" edges="169413591#0 561929987 563791824 265903506#0 265903506#2 265903506#3 265903506#4 265903506#5 265903506#6 265903506#7 265903506#8 265903506#9 265903506#10 265903506#11 265903506#12 265903506#13 265903506#14 265903506#15 265903506#16 265903506#17 265903506#18 265903506#19 265903506#20 265903506#21 265903506#22 614072011 614072017#0 614072017#1-AddedOnRampEdge 614072017#1 614072017#2 176492657 1516045286 561929986#0 561929986#1 561929986#3 561929986#4 611866622#0 611866615#2 583910213#0 583910213#1 583910213#2 583910213#3 1108471058 673792809#0 673792809#1 673792808#1 585446283#0 730290861#1 24563348#0 24563348#1 24563348#3 24563348#4 24563348#7 24563348#8 24563348#9 24563348#9-AddedOffRampEdge 24563348#10 24563348#11 678397112 678397111#0 678397111#1 678397111#2 680551213 680551205 24563333#0 24563333#1 24563333#2 24563333#3 24563333#4 39013511#0 39013511#1 39013511#2 39013511#3 39013511#6 39013511#7 39013511#8 39013511#9 39013511#10 39013511#13 39013511#14 39013511#15 39013511#16 77339658 77339655#0 77339655#1 77339655#3 77339655#4 77339655#8 77339655#9 730237457#0 730237457#3 1451897494-AddedOnRampEdge 1451897494 1451897494-AddedOffRampEdge 77015779#1 715377036-AddedOnRampEdge 715377036 77349488#1 77349488#2 77349488#3 77349488#4 77349488#5 584241782 37751254#0 37751254#1 37751254#2 760525680 566680381-AddedOnRampEdge 566680381 1313030094 39013521 1313030095 586156360#1 586156360#2 586156360#3 566009660#0 733576742 566680388#4 586156365#1 586156365#2 586156365#3 44317039 39013518 312031900 37751255#0 37751255#1 584241795#0 584241795#1 584241794 202645529#0 202645529#1 202645529#2 1312806548 696618571#1 80439704#0 80439704#1 80439704#2 80439704#3 80439704#4 176466571 1076237280#2 176466583" >
        <stop busStop="5426388558" duration="20" until="669.0"/> <!-- Nehru Nagar -->
        <stop busStop="5584870725" duration="20" until="751.0"/> <!-- Ashram -->
        <stop busStop="938635590" duration="20" until="885.0"/> <!-- Nizamuddin Railway Station -->
    </route>
    <route id="pt_bus_418A:0" edges="77339656#11 77339656#12 77339656#13 680551215 561759719#0 561759719#1 561759719#2 561759719#3 561759719#4 678397108 678397106 678397105 555242574-AddedOnRampEdge 555242574 77349464#0 77349464#1 77349464#1-AddedOffRampEdge 77349464#2 562479736#0 562479736#1 562479736#3 562479736#4 562479736#5-AddedOnRampEdge 562479736#5 562479736#7 585446277#1" >
        <stop busStop="6371764317" duration="20" until="53.0"/> <!-- Hazarat Nizamuddin -->
        <stop busStop="5342182750" duration="20" until="186.0"/> <!-- None -->
        <stop busStop="5342182505" duration="20" until="250.0"/> <!-- None -->
    </route>
    <route id="pt_bus_427:0" edges="584241789#1 1203083884 1203083883#1 1203083883#3 176466591#1 176466591#2 176466591#3 176466591#4 176466591#5 584241787 1451897494-AddedOnRampEdge 1451897494 1451897494-AddedOffRampEdge 77015779#1 715377036-AddedOnRampEdge 715377036 77349488#1 77349488#2 77349488#3 77349488#4 77349488#5 584241782 37751254#0 37751254#1 37751254#2 760525680 566680381-AddedOnRampEdge 566680381 1313030094 39013521 1313030095 586156360#1 586156360#2 586156360#3 566009660#0 566009660#1 566009660#3" >
        <stop busStop="938635417" duration="20" until="36.0"/> <!-- Nizamuddin Railway Station -->
        <stop busStop="5584872921" duration="20" until="164.0"/> <!-- Ashram -->
        <stop busStop="5426389543" duration="20" until="285.0"/> <!-- Nehru Nagar -->
        <stop busStop="5430723253" duration="20" until="338.0"/> <!-- Sri Niwas Puri -->
    </route>
    <route id="pt_bus_427:1" edges="566680388#0 566680388#1 566680388#2 566680388#3 566680388#4 586156365#1 586156365#2 586156365#3 44317039 39013518 312031900 37751255#0 37751255#1 584241795#0 584241795#1 584241794 202645529#0 202645529#1 202645529#2 1312806548 696618571#1 80439704#0 80439704#1 80439704#2 80439704#3 80439704#4 176466571 1076237280#2 176466583" >
        <stop busStop="5426388558" duration="20" until="75.0"/> <!-- Nehru Nagar -->
        <stop busStop="5584870725" duration="20" until="158.0"/> <!-- Ashram -->
        <stop busStop="938635590" duration="20" until="302.0"/> <!-- Nizamuddin Railway Station -->
    </route>
    <route id="pt_bus_442:0" edges="28746245 1457651694 676708027 676708027-AddedOffRampEdge 1451903122 570427347 43359324 565938868#0-AddedOnRampEdge 565938868#0 677074043 1420705472#1 1420705472#2 1420705472#3 1420705472#4 1420705475 565938871#2 565938871#3 565938871#4 565938871#5 565938870 44316345 563679828 44316346" >
        <stop busStop="4819437823" duration="20" until="190.0"/> <!-- Safdarjung Hospital -->
        <stop busStop="5426388566" duration="20" until="344.0"/> <!-- South Extension -->
    </route>
    <route id="pt_bus_443:0" edges="76834871 211191578 852601469#0 852601469#1 852601469#2 852601468#0 852601468#1 852601468#2" >
        <stop busStop="7242732172" duration="20" until="68.0"/> <!-- Temporary Stop -->
        <stop busStop="6497707582" duration="20" until="132.0"/> <!-- Delhi Police Apartment -->
    </route>
    <route id="pt_bus_450:0" edges="-653235647#0 -38116089#12 -38116089#11 -38116089#10 -38116089#9 -38116089#8 -38116089#7 -38116090#4 -1076000734 -424007912#2 -424007912#1 -1202758360 -424014386 168275206#0 168275206#1 -424014365#6 -424014365#5 -424014365#4 -424014365#3 1306749688 -38116089#1 652047004 583620105#1 583620105#2 583620105#3 583620105#4 583620105#5 168381546#0 168381546#1 44317041#0 44317041#1 44317041#2 44317041#3 44317041#4 44317041#5" >
        <stop busStop="-6122143946" duration="20" until="35.0"/> <!-- Jal Vihar Terminal -->
        <stop busStop="6203988021" duration="20" until="231.0"/> <!-- Lajpat Nagar (DJB) -->
    </route>
    <route id="pt_bus_450:1" edges="80958874#0 80958874#1 80958874#2 80958874#5 80958874#6 80958874#7 80958874#8 80958874#9 80958874#10 80958874#11 80958874#12 80958874#13 80958874#14 80958874#15 730290860#0 730290860#4 730290860#5 673792811#0 673792811#1 673792810#0 673792810#1 673792810#2 673792810#3 673792810#4 611866613#0 611866617#1 561929985#0 561929985#1 1306337530 1306337529#0 1306337529#1 176492656 1516045288 176492655#1 614072012#0 614072012#1 563791819#0 563791819#1 563791819#2 563791819#3 563791819#4 563791819#5 563791819#6 563791819#7 563791819#8 563791819#9 563791819#10 563791819#11 563791822#0 563791822#1 563679829#0 563679829#1-AddedOnRampEdge 563679829#1 563679829#2 44316346" >
        <stop busStop="7019144405" duration="20" until="47.0"/> <!-- Sujan Singh Park -->
        <stop busStop="5426388555" duration="20" until="126.0"/> <!-- Dayal Singh College -->
        <stop busStop="5432771968" duration="20" until="245.0"/> <!-- Pragati Vihar -->
        <stop busStop="2578295203" duration="20" until="334.0"/> <!-- Jawaharlal Nehru Stadium -->
        <stop busStop="6786032368" duration="20" until="425.0"/> <!-- Sukhdev Vihar -->
        <stop busStop="5431738836" duration="20" until="483.0"/> <!-- Defence Colony (Homeopathic College) -->
        <stop busStop="1694776065" duration="20" until="541.0"/> <!-- PT College (Kotla) -->
        <stop busStop="6112155497" duration="20" until="648.0"/> <!-- Andrews Ganj -->
    </route>
    <route id="pt_bus_460:0" edges="662141606#0 662141606#4 662141606#4-AddedOffRampEdge 662141606#5 662141606#6 39013515#0 39013515#1 760525680 566680381-AddedOnRampEdge 566680381 1313030094 39013521 1313030095 566680382 1313027075" >
        <stop busStop="6198752458" duration="20" until="82.0"/> <!-- New Friends Colony -->
        <stop busStop="910451189" duration="20" until="155.0"/> <!-- Ashram -->
        <stop busStop="5585958328" duration="20" until="229.0"/> <!-- Nehru Nagar -->
    </route>
    <route id="pt_bus_469:0" edges="566680388#0 566680388#1 566680388#2 566680388#3 566680388#4 586156365#1 586156365#2 586156365#3 44317039 39013518 312031900 37751255#0 37751255#1 584241795#0 584241795#1 657413479 581239050#0 581239050#1 581239050#2 555197196#0 555197196#1 555197196#2 555197196#3 555197196#4 39013523#1 39013523#2 39013523#3 39013523#4 39013523#5 39013523#6 39013523#7 70258965#0 70258965#1 70258965#2 70258965#3 170767287#0 170767287#1 170767287#2 170767287#3 77349489#1 77349489#2 77349489#3 77349489#4 77349489#5 77349489#6 1491586823 70258954#1 70258954#3 70258954#4 70258954#5 555197204 679512999-AddedOnRampEdge 679512999 679512999-AddedOffRampEdge 812684509 631795142 76834907#1 76834908 682971785 76834886#1 682971783 682971782 555197220#0 555197220#1 813012744" >
        <stop busStop="5426388558" duration="20" until="75.0"/> <!-- Nehru Nagar -->
        <stop busStop="5121928122" duration="20" until="202.0"/> <!-- Maharani Bagh -->
        <stop busStop="5121928125" duration="20" until="299.0"/> <!-- Gurudwara Bala Sahib -->
        <stop busStop="5121928128" duration="20" until="402.0"/> <!-- Sarai Kale Khan -->
        <stop busStop="5121928130" duration="20" until="466.0"/> <!-- Sarai Kale Khan ISBT -->
        <stop busStop="6396989742" duration="20" until="700.0"/> <!-- Khel Gaon -->
    </route>
    <route id="pt_bus_479:0" edges="28746245 1457651694 676708027 676708027-AddedOffRampEdge 1451903122 570427347 43359324 565938868#0-AddedOnRampEdge 565938868#0 677074043 1420705472#1 1420705472#2 1420705472#3 1420705472#4 1420705475 565938871#2 565938871#3 565938871#4 565938871#5 565938870 44316345 563679828 44316346" >
        <stop busStop="4819437823" duration="20" until="105.0"/> <!-- Safdarjung Hospital -->
        <stop busStop="5426388566" duration="20" until="253.0"/> <!-- South Extension -->
    </route>
    <route id="pt_bus_479A:0" edges="28746245 1457651694 676708027 676708027-AddedOffRampEdge 1451903122 570427347 43359324 565938868#0-AddedOnRampEdge 565938868#0 677074043 1420705472#1 1420705472#2 1420705472#3 1420705472#4 1420705475 565938871#2 565938871#3 565938871#4 565938871#5 565938870 44316345 563679828 44316346" >
        <stop busStop="4819437823" duration="20" until="84.0"/> <!-- Safdarjung Hospital -->
        <stop busStop="5426388566" duration="20" until="229.0"/> <!-- South Extension -->
        <stop busStop="6112155497" duration="20" until="357.0"/> <!-- Andrews Ganj -->
    </route>
    <route id="pt_bus_492:0" edges="566680388#0 566680388#1 566680388#2 566680388#3 566680388#4 586156365#1 586156365#2 586156365#3 44317039 39013518 312031900 37751255#0 37751255#1 584241795#0 584241795#1 657413479 581239050#0 581239050#1 581239050#2 555197196#0 555197196#1 555197196#2 555197196#3 555197196#4 39013523#1 39013523#2 39013523#3 39013523#4 39013523#5 39013523#6 39013523#7 70258965#0 70258965#1 70258965#2 70258965#3 170767287#0 170767287#1 170767287#2 170767287#3 77349489#1 77349489#2 77349489#3 77349489#4 77349489#5 77349489#6 1491586823 70258954#1 70258954#3 70258954#4 70258954#5 555197204 679512999-AddedOnRampEdge 679512999 679512999-AddedOffRampEdge 812684509 631795142 76834907#1 76834908 682971785 76834886#1 682971783 682971782 555197220#0 76834871 211191578 852601469#0 852601469#1 852601469#2 852601468#0 852601468#1 852601468#2" >
        <stop busStop="6497625779" duration="20" until="60.0"/> <!-- PGDAV College -->
        <stop busStop="5426388558" duration="20" until="119.0"/> <!-- Nehru Nagar -->
        <stop busStop="6395693844" duration="20" until="268.0"/> <!-- Maharani Bagh -->
        <stop busStop="5121928125" duration="20" until="366.0"/> <!-- Gurudwara Bala Sahib -->
        <stop busStop="5121928128" duration="20" until="471.0"/> <!-- Sarai Kale Khan -->
        <stop busStop="5121928130" duration="20" until="537.0"/> <!-- Sarai Kale Khan ISBT -->
        <stop busStop="7171446389" duration="20" until="719.0"/> <!-- PWD Office -->
        <stop busStop="6396989742" duration="20" until="805.0" jump="53.51221107152039"/> <!-- Khel Gaon -->
        <stop busStop="7242732172" duration="20" until="924.5122110715204"/> <!-- Temporary Stop -->
        <stop busStop="6497707582" duration="20" until="988.5122110715204"/> <!-- Delhi Police Apartment -->
    </route>
    <route id="pt_bus_519:0" edges="29534879 654175709#0 654175709#1 654175709#2 654175709#3 582367349#3 582367349#4 582367349#4-AddedOffRampEdge 80515440 583143702-AddedOnRampEdge 583143702 676708026#0 676708026#1 689446382 689446381 683766463 28616702#0 28616702#1 571249177#0 571249177#1 571168753#0 571168753#1 571168753#2 571168752 571168756 676708024" >
        <stop busStop="5732543211" duration="20" until="64.0"/> <!-- A.I.I.M.S. -->
        <stop busStop="5541755269" duration="20" until="151.0"/> <!-- Kidwai Nagar -->
        <stop busStop="6336918971" duration="20" until="278.0"/> <!-- Safdarjung Terminal -->
    </route>
    <route id="pt_bus_534:0" edges="37703539#0 37703539#2 37703539#4 37703539#5 37703539#6 37703539#8 37703539#9 37703539#10 37703539#12 37703539#13 25457965#0 -1308944423 39013523#2 39013523#3 39013523#4 39013523#5 39013523#6 39013523#7 70258965#0 70258965#1 70258965#2 70258965#3 170767287#0 170767287#1 170767287#2 170767287#3 77349489#1 77349489#2 77349489#3 77349489#4 77349489#5 77349489#6 1491586823 70258954#1 70258954#3 70258954#4 70258954#5 555197204 679512999-AddedOnRampEdge 679512999 679512999-AddedOffRampEdge 812684509 631795142 76834907#1 76834908 682971785 76834886#1 682971783 682971782 555197220#0 555197220#1 813012744" >
        <stop busStop="5121928122" duration="20" until="178.0"/> <!-- Maharani Bagh -->
        <stop busStop="5121928125" duration="20" until="273.0"/> <!-- Gurudwara Bala Sahib -->
        <stop busStop="5121928128" duration="20" until="380.0"/> <!-- Sarai Kale Khan -->
        <stop busStop="5121928130" duration="20" until="444.0"/> <!-- Sarai Kale Khan ISBT -->
        <stop busStop="7171446389" duration="20" until="627.0"/> <!-- PWD Office -->
        <stop busStop="6396989742" duration="20" until="714.0"/> <!-- Khel Gaon -->
    </route>
    <route id="pt_bus_534A:0" edges="37703539#0 37703539#2 37703539#4 37703539#5 37703539#6 37703539#8 37703539#9 37703539#10 37703539#12 37703539#13 25457965#0 -1308944423 39013523#2 39013523#3 39013523#4 39013523#5 39013523#6 39013523#7 70258965#0 70258965#1 70258965#2 70258965#3 170767287#0 170767287#1 170767287#2 170767287#3 77349489#1 77349489#2 77349489#3 77349489#4 77349489#5 77349489#6 1491586823 70258954#1 70258954#3 70258954#4 70258954#5 555197204 679512999-AddedOnRampEdge 679512999 679512999-AddedOffRampEdge 812684509 631795142 76834907#1 76834908 682971785 76834886#1 682971783 682971782 555197220#0 555197220#1 813012744" >
        <stop busStop="5121928122" duration="20" until="203.0"/> <!-- Maharani Bagh -->
        <stop busStop="5121928125" duration="20" until="301.0"/> <!-- Gurudwara Bala Sahib -->
        <stop busStop="5121928128" duration="20" until="408.0"/> <!-- Sarai Kale Khan -->
        <stop busStop="5121928130" duration="20" until="471.0"/> <!-- Sarai Kale Khan ISBT -->
        <stop busStop="7171446389" duration="20" until="654.0"/> <!-- PWD Office -->
    </route>
    <route id="pt_bus_543:0" edges="28746245 1457651694 676708027 676708027-AddedOffRampEdge 1451903122 570427347 43359324 565938868#0-AddedOnRampEdge 565938868#0 677074043 1420705472#1 1420705472#2 1420705472#3 1420705472#4 1420705475 565938871#2 -265763304#3 26664728#3 26664728#4 26664728#5 26664728#6 26664728#7 26664728#8 686625277 686625276 169413610 265903506#0 265903506#2 265903506#3 265903506#4 265903506#5 265903506#6 265903506#7 265903506#8 265903506#9 265903506#10 265903506#11 265903506#12 265903506#13 265903506#14 265903506#15 265903506#16 265903506#17 265903506#18 265903506#19 265903506#20 265903506#21 265903506#22 614072011 614072017#0 614072017#1-AddedOnRampEdge 614072017#1 614072017#2 176492657 1516045286 561929986#0 561929986#1 561929986#3 561929986#4 611866622#0 611866615#2 583910213#0 583910213#1 583910213#2 583910213#3 1108471058 673792809#0 673792809#1 673792808#1 585446283#0 730290861#1 24563348#0 24563348#1 24563348#3 24563348#4 24563348#7 24563348#8 24563348#9 24563348#9-AddedOffRampEdge 24563348#10 24563348#11 678397112 678397111#0 678397111#1 678397111#2 680551213 680551205 24563333#0 24563333#1 24563333#2 24563333#3 24563333#4 39013511#0 39013511#1 39013511#2 39013511#3 39013511#6 39013511#7 39013511#8 39013511#9 39013511#10 39013511#13 39013511#14 39013511#15 39013511#16 77339658 77339655#0 77339655#1 77339655#3 77339655#4 77339655#8 77339655#9 730237457#0 730237457#3 1451897494-AddedOnRampEdge 1451897494 1451897494-AddedOffRampEdge 77015779#1 715377036-AddedOnRampEdge 715377036 77349488#1 77349488#2 77349488#3 77349488#4 77349488#5 584241782 37751254#0 37751254#1 37751254#2 760525680 566680381-AddedOnRampEdge 566680381 1313030094 39013521 1313030095 586156360#1 586156360#2 586156360#3 566009660#0 733576742 566680388#4 586156365#1 586156365#2 586156365#3 44317039 39013518 312031900 37751255#0 37751255#1 584241795#0 584241795#1 657413479 581239050#0 581239050#1 581239050#2 555197196#0 555197196#1 555197196#2 555197196#3 555197196#4 39013523#1 39013523#2 39013523#3 39013523#4 39013523#5 39013523#6 39013523#7 70258965#0 70258965#1 70258965#2 1123531345 170767287#1 170767287#2 170767287#3 77349489#1 77349489#2 77349489#3 77349489#4 77349489#5 77349489#6 1491586823 70258954#1 70258954#3 70258954#4 70258954#5 555197204 679512999-AddedOnRampEdge 679512999 679512999-AddedOffRampEdge 812684509 631795142 76834907#1 76834908 682971785 76834886#1 682971783 682971782 555197220#0 555197220#1 813012744" >
        <stop busStop="4819437823" duration="20" until="73.0"/> <!-- Safdarjung Hospital -->
        <stop busStop="5426391723" duration="20" until="225.0"/> <!-- South Extension -->
        <stop busStop="5426388558" duration="20" until="763.0"/> <!-- Nehru Nagar -->
        <stop busStop="5121928122" duration="20" until="866.0"/> <!-- Maharani Bagh -->
        <stop busStop="5121928128" duration="20" until="1026.0"/> <!-- Sarai Kale Khan -->
        <stop busStop="5121928130" duration="20" until="1091.0"/> <!-- Sarai Kale Khan ISBT -->
        <stop busStop="6396989742" duration="20" until="1325.0"/> <!-- Khel Gaon -->
    </route>
    <route id="pt_bus_543A:0" edges="28746245 1457651694 676708027 676708027-AddedOffRampEdge 1451903122 570427347 43359324 565938868#0-AddedOnRampEdge 565938868#0 677074043 1420705472#1 1420705472#2 1420705472#3 1420705472#4 1420705475 565938871#2" >
        <stop busStop="4819437823" duration="20" until="190.0"/> <!-- Safdarjung Hospital -->
        <stop busStop="5426388566" duration="20" until="343.0"/> <!-- South Extension -->
    </route>
    <route id="pt_bus_543B:0" edges="28746245 1457651694 676708027 676708027-AddedOffRampEdge 1451903122 570427347 43359324 565938868#0-AddedOnRampEdge 565938868#0 677074043 1420705472#1 1420705472#2 1420705472#3 1420705472#4 1420705475 565938871#2 565938871#3 565938871#4 565938871#5 565938870 44316345 563679828 44316346" >
        <stop busStop="4819437823" duration="20" until="232.0"/> <!-- Safdarjung Hospital -->
        <stop busStop="5426388566" duration="20" until="386.0"/> <!-- South Extension -->
        <stop busStop="6112155497" duration="20" until="515.0"/> <!-- Andrews Ganj -->
    </route>
    <route id="pt_bus_544:0" edges="28746245 1457651694 676708027 676708027-AddedOffRampEdge 1451903122 570427347 43359324 565938868#0-AddedOnRampEdge 565938868#0 677074043 1420705472#1 1420705472#2 1420705472#3 1420705472#4 1420705475 565938871#2 -265763304#3 26664728#3 26664728#4 26664728#5 26664728#6 26664728#7 26664728#8 686625277 686625276 732001899#0 565347502 265903505 590522606#0 265940883#0 265940883#1 265940883#2" >
        <stop busStop="4819437823" duration="20" until="67.0"/> <!-- Safdarjung Hospital -->
        <stop busStop="5426388566" duration="20" until="215.0"/> <!-- South Extension -->
    </route>
    <route id="pt_bus_578:0" edges="28746245 1457651694 44315457#0 44315457#1 812690414 812690415#1 812690415#2 676708026#0 676708026#1 689446382 689446381 683766463 28616702#0 28616702#1 571249177#0 571249177#1 571168753#0 571168753#1 571168753#2 571168752 571168756 676708024" >
        <stop busStop="4819437823" duration="20" until="58.0"/> <!-- Safdarjung Hospital -->
        <stop busStop="5541755269" duration="20" until="194.0"/> <!-- Kidwai Nagar -->
        <stop busStop="6336918971" duration="20" until="318.0"/> <!-- Safdarjung Terminal -->
    </route>
    <route id="pt_bus_611:0" edges="28746245 1457651694 676708027 676708027-AddedOffRampEdge 1451903122 570427347 43359324 565938868#0-AddedOnRampEdge 565938868#0 677074043 1420705472#1 1420705472#2 1420705472#3 1420705472#4 1420705475 565938871#2 565938871#3 565938871#4 565938871#5 565938870 44316345 563679828 44316346" >
        <stop busStop="5426388566" duration="20" until="162.0"/> <!-- South Extension -->
        <stop busStop="6112155497" duration="20" until="293.0"/> <!-- Andrews Ganj -->
    </route>
    <route id="pt_bus_623:0" edges="28746245 1457651694 676708027 676708027-AddedOffRampEdge 1451903122 570427347 43359324 565938868#0-AddedOnRampEdge 565938868#0 677074043 1420705472#1 1420705472#2 1420705472#3 1420705472#4 1420705475 565938871#2 -265763304#3 26664728#3 26664728#4 26664728#5 26664728#6 26664728#7 26664728#8 686625277 686625276 169413610 265903506#0 265903506#2 265903506#3 265903506#4 265903506#5 265903506#6 265903506#7 265903506#8 265903506#9 265903506#10 265903506#11 265903506#12 265903506#13 265903506#14 265903506#15 265903506#16 265903506#17 265903506#18 265903506#19 265903506#20 265903506#21 265903506#22 614072011 614072017#0 614072017#1-AddedOnRampEdge 614072017#1 614072017#2 176492657 1516045286 561929986#0 561929986#1 561929986#3 561929986#4 611866622#0 611866615#2 583910213#0 583910213#1 583910213#2 583910213#3 1108471058 673792809#0 673792809#1 673792808#1 585446283#0 176492654#2 176492654#3 176492654#4 176492654#5 176492654#6 176492654#7 176492654#8 176492654#11 176492654#12 176492654#13 176492654#14 176492654#15 176492654#18 176492654#19 1187268491#0 1187268491#1 1187268491#2 1187268490 24577364#0 24577364#1 1077595194 -24577367#8 -24577367#7 -24577367#6 -24577367#4 -24577367#2 -24577367#1 -24577367#0 1077595195#1 732001894 581989172#0 581989172#1 604050032 24577379#0 24577379#1 24577379#2 582461174#0 582461174#1 582461174#2 296963058#0 296963058#1 296963058#2 296963058#3 296963058#4 296963058#5 296963058#6 296963058#7" >
        <stop busStop="4819437823" duration="20" until="80.0"/> <!-- Safdarjung Hospital -->
        <stop busStop="5426388566" duration="20" until="226.0"/> <!-- South Extension -->
        <stop busStop="6766175603" duration="20" until="340.0"/> <!-- PT College (Kotla) -->
        <stop busStop="6766995948" duration="20" until="397.0"/> <!-- Defence Colony (Homeopathic College) -->
        <stop busStop="5701997798" duration="20" until="454.0"/> <!-- Sukhdev Vihar -->
        <stop busStop="6449436641" duration="20" until="522.0"/> <!-- Seva Nagar Flyover -->
        <stop busStop="2578295201" duration="20" until="592.0"/> <!-- Jawaharlal Nehru Stadium -->
        <stop busStop="7655631092" duration="20" until="665.0"/> <!-- Pragati Vihar -->
        <stop busStop="5426390921" duration="20" until="736.0"/> <!-- Dayal Singh College -->
        <stop busStop="7655631102" duration="20" until="802.0"/> <!-- Bharti Nagar -->
        <stop busStop="355435748" duration="20" until="861.0"/> <!-- Sujan Singh Park -->
        <stop busStop="5732544103" duration="20" until="1046.0"/> <!-- Shahjahan Road UPSC -->
    </route>
    <route id="pt_bus_623:1" edges="680551206 680551212#0 680551212#1 680551212#2 296963059#0 296963059#1 296963059#2 1126646522#0 24577367#0 24577367#1 24577367#2 24577367#4 24577367#6 24577367#7 24577367#8 1126646523 783084113#1 783084113#2 732001895#0 732001905 1187268486 1187268489#0 1187268489#1 732001908#0 732001908#1 1187268492#1 80958874#0 80958874#1 80958874#2 80958874#5 80958874#6 80958874#7 80958874#8 80958874#9 80958874#10 80958874#11 80958874#12 80958874#13 80958874#14 80958874#15 730290860#0 730290860#4 730290860#5 673792811#0 673792811#1 673792810#0 673792810#1 673792810#2 673792810#3 673792810#4 611866613#0 611866617#1 561929985#0 561929985#1 1306337530 1306337529#0 1306337529#1 176492656 1516045288 176492655#1 614072012#0 1071586270 614072011 614072017#0 614072017#1-AddedOnRampEdge 614072017#1 614072017#2 176492657 1516045286 561929986#0 561929986#1 561929986#3 561929986#4 611866622#0 611866617#1 561929985#0 561929985#1 1306337530 1306337529#0 1306337529#1 176492656 1516045288 176492655#1 614072012#0 614072012#1 563791819#0 563791819#1 563791819#2 563791819#3 563791819#4 563791819#5 563791819#6 563791819#7 563791819#8 563791819#9 563791819#10 563791819#11 563791822#0 563791822#1 265903505 565938869 562340226#1 562340226#2 562340226#3 562340226#4 -1340866550 1238027420#4 1305032092#0 1305032092#1 1305032092#2 1305032092#3 242476849#1 686575741 28412393#5 28412393#6 690251619 564173145 44315450 1313474874 44315451#0 44315451#1" >
        <stop busStop="6854465827" duration="20" until="124.0"/> <!-- Humayun Road -->
        <stop busStop="5426389916" duration="20" until="220.0"/> <!-- Sujan Singh Park -->
        <stop busStop="7062645321" duration="20" until="337.0"/> <!-- Bharti Nagar -->
        <stop busStop="5426388555" duration="20" until="404.0"/> <!-- Dayal Singh College -->
        <stop busStop="5432771968" duration="20" until="538.0"/> <!-- Pragati Vihar -->
        <stop busStop="7655302453" duration="20" until="643.0"/> <!-- None -->
        <stop busStop="5248673897" duration="20" until="798.0"/> <!-- Jawaharlal Nehru Stadium -->
        <stop busStop="7167030420" duration="20" until="867.0"/> <!-- Seva Nagar Flyover -->
        <stop busStop="6786032368" duration="20" until="936.0"/> <!-- Sukhdev Vihar -->
        <stop busStop="5431738836" duration="20" until="993.0"/> <!-- Defence Colony (Homeopathic College) -->
        <stop busStop="1694776065" duration="20" until="1051.0"/> <!-- PT College (Kotla) -->
        <stop busStop="5426391318" duration="20" until="1134.0"/> <!-- South Extension -->
        <stop busStop="4819415322" duration="20" until="1235.0"/> <!-- All India Institute of Medical Sciences -->
    </route>
    <route id="pt_bus_624A:0" edges="28746245 1457651694 44315457#0 44315457#1 812690414 812690415#1 812690415#2 676708026#0 676708026#1 689446382 689446381" >
        <stop busStop="4819437823" duration="20" until="227.0"/> <!-- Safdarjung Hospital -->
        <stop busStop="5541755269" duration="20" until="334.0"/> <!-- Kidwai Nagar -->
    </route>
    <route id="pt_bus_724:0" edges="28746245 1457651694 676708027 676708027-AddedOffRampEdge 1451903122 570427347 43359324 565938868#0-AddedOnRampEdge 565938868#0 677074043 1420705472#1 1420705472#2 1420705472#3 1420705472#4 1420705475 565938871#2 565938871#3 565938871#4 565938871#5 565938870 44316345 563679828 44316346" >
        <stop busStop="4819437823" duration="20" until="223.0"/> <!-- Safdarjung Hospital -->
        <stop busStop="5426388566" duration="20" until="377.0"/> <!-- South Extension -->
    </route>
    <route id="pt_bus_727:0" edges="28746245 1457651694 676708027 676708027-AddedOffRampEdge 1451903122 570427347 43359324 565938868#0-AddedOnRampEdge 565938868#0 677074043 1420705472#1 1420705472#2 1420705472#3 1420705472#4 1420705475 565938871#2 565938871#3 565938871#4 565938871#5 565938870 44316345 563679828 44316346" >
        <stop busStop="4819437823" duration="20" until="57.0"/> <!-- Safdarjung Hospital -->
        <stop busStop="5426388566" duration="20" until="204.0"/> <!-- South Extension -->
    </route>
    <route id="pt_bus_794:0" edges="562340228#0 562340228#1 562340228#2 1253187154#0 1253187154#1 1071482500#5 1071482500#6 1071482500#7 1071482500#8 1071482500#9 1187268512#7 1187268512#8 1187268512#9 1108471058 673792809#0 673792809#1 673792808#1 585446283#0 730290861#1 24563348#0 24563348#1 24563348#3 24563348#4 24563348#7 24563348#8 24563348#9 24563348#9-AddedOffRampEdge 24563348#10 24563348#11 678397112 678397111#0 678397111#1 678397111#2 680551213 680551205 24563333#0 24563333#1 24563333#2 24563333#3 24563333#4 39013511#0 39013511#1 39013511#2 39013511#3 39013511#6 39013511#7 39013511#8 39013511#9 39013511#10 39013511#13 39013511#14 163778522#0 163778522#1 176466583 584241792 80440842#1 584241789#0 584241789#1 1203083884 1203083883#1 1203083883#3 176466591#1 176466591#2 176466591#3 176466591#4 176466591#5 584241784#0 584241793#0 584241793#4 1090402162 77339656#0 77339656#1 77339656#4 77339656#5 77339656#6 77339656#11 77339656#12 77339656#13 680551215 561759719#0 561759719#1 561759719#2 561759719#3 561759719#4 678397108 678397107#0 678397107#1 561759718#0 561759718#1 561759718#2 561759718#3 561759718#4 561759718#5 585446272#0 169222358#1 169222358#2 169222358#3 169222358#4 611866609#0 611866609#1 611866609#2 169222363#0 169222363#1 169222363#2-AddedOnRampEdge 169222363#2 169222366#4 169222366#5 176492666 176492666-AddedOffRampEdge 611866618#0 611866621#1 562340228#0 562340228#1 562340228#2 1253187154#0 1253187154#1 -562340230#3 -562340230#1 -562340230#0 -766036533#1 -766036533#0 132087598#5 132087598#6 766036523#3 766036523#4 45323444 1541038918#1 1541038918#3 1541038918#4 1541038918#5 1541038918#6 1541038918#7 1541038918#8 1541038918#9 1541038918#10 1541038918#12 1541038918#13 571167486 758753871 571167485#0 774999421 1539359564 1312986297-AddedOnRampEdge 1312986297 1312986297-AddedOffRampEdge 683766456 683766453#0 683766453#1 31756485#0 31756485#1 31756485#2 31756485#3 31756485#4 722082934#0 1489755478 1238026854#3 1238026855 722082934#2-AddedOnRampEdge 722082934#2 722082934#2-AddedOffRampEdge 581439206 581439207 581439225 377280468 44315451#0 44315451#1" >
        <stop busStop="938635417" duration="20" until="392.0"/> <!-- Nizamuddin Railway Station -->
        <stop busStop="5441523402" duration="20" until="722.0"/> <!-- Central School Lodhi Road -->
        <stop busStop="-7154453335" duration="20" until="807.0"/> <!-- Lodhi Colony Market -->
        <stop busStop="5715392714" duration="20" until="882.0"/> <!-- Lodhi Colony -->
        <stop busStop="5483332132" duration="20" until="1003.0"/> <!-- Safdarjung Airport -->
        <stop busStop="5483331962" duration="20" until="1137.0"/> <!-- Kidwai Nagar -->
    </route>
    <route id="pt_bus_794:1" edges="676708026#0 676708026#1 689446382 689446381 683766464 683766462 683766462-AddedOffRampEdge 1539359559 1312986298 370543236 1312986296 774999418#0 774999418#1 31756484#0 31756484#1 31756484#2 31756484#3 31756484#5 31756484#6 31756484#7 31756484#8 31756484#9 31756484#10 31756484#11 31756484#12 760525673 265032208#0 265032208#1 265032208#2 -1541038918#13 -1541038918#12 -1541038918#10 -1541038918#9 -1541038918#8 -1541038918#7 -1541038918#6 -1541038918#5 -1541038918#4 -1541038918#3 -1541038918#1 -1541038918#0 -766036523#4 -766036523#3 -766036523#2 -766036523#1 -766036523#0 766036524 766036529#0 766036529#1 562340230#0 562340230#1 562340230#3 176492665#0 176492665#1 611866611#0 611866612#1 563679831-AddedOnRampEdge 563679831 169222366#7 169222366#1 169222366#2 169222364#0 169222364#1 169222364#3 169222364#4 169222364#5 169222364#6 169222364#7 169222364#8 169222364#9 169222364#10 24563348#3 24563348#4 24563348#7 24563348#8 24563348#9 24563348#9-AddedOffRampEdge 24563348#10 24563348#11 678397112 678397111#0 678397111#1 678397111#2 680551213 680551205 24563333#0 24563333#1 24563333#2 24563333#3 24563333#4 39013511#0 39013511#1 39013511#2 39013511#3 39013511#6 39013511#7 39013511#8 39013511#9 39013511#10 39013511#13 39013511#14 163778522#0 163778522#1 176466583" >
        <stop busStop="5541755269" duration="20" until="61.0"/> <!-- Kidwai Nagar -->
        <stop busStop="5541755268" duration="20" until="190.0"/> <!-- None -->
        <stop busStop="5732542138" duration="20" until="232.0"/> <!-- Safdarjung Airport -->
        <stop busStop="5732543997" duration="20" until="299.0"/> <!-- Safdarjung Madrasa -->
        <stop busStop="-5715393721" duration="20" until="444.0"/> <!-- Lodhi Colony -->
        <stop busStop="5441523433" duration="20" until="523.0"/> <!-- Lodhi Colony Block 12-13 -->
        <stop busStop="5441522259" duration="20" until="592.0"/> <!-- Central School Lodhi Road -->
        <stop busStop="938635590" duration="20" until="943.0"/> <!-- Nizamuddin Railway Station -->
    </route>
    <route id="pt_bus_966:0" edges="584241789#1 1203083884 1203083883#1 1203083883#3 176466591#1 176466591#2 176466591#3 176466591#4 176466591#5" >
        <stop busStop="938635417" duration="20" until="36.0"/> <!-- Nizamuddin Railway Station -->
    </route>
    <route id="pt_bus_966:1" edges="80439704#0 80439704#1 80439704#2 80439704#3 80439704#4 176466571 1076237280#2 176466583" >
        <stop busStop="938635590" duration="20" until="74.0"/> <!-- Nizamuddin Railway Station -->
    </route>
    <route id="pt_bus_966EX:0" edges="176466583" >
        <stop busStop="938635590" duration="20" until="48.0"/> <!-- Nizamuddin Railway Station -->
    </route>
    <route id="pt_bus_984A:0" edges="28746245 1457651694 676708027 676708027-AddedOffRampEdge 1451903122 570427347 43359324 565938868#0-AddedOnRampEdge 565938868#0 677074043 1420705472#1 1420705472#2 1420705472#3 1420705472#4 1420705475 565938871#2 565938871#3 565938871#4 565938871#5 565938870 44316345 563679828 44316346" >
        <stop busStop="4819437823" duration="20" until="57.0"/> <!-- Safdarjung Hospital -->
        <stop busStop="5426388566" duration="20" until="201.0"/> <!-- South Extension -->
        <stop busStop="6112155497" duration="20" until="329.0"/> <!-- Andrews Ganj -->
    </route>
    <route id="pt_bus_BPExp:0" edges="679552303 1313465446 70258960#0 70258960#1 70258963#0 70258963#1 70258963#2 1491586817" >
        <stop busStop="6362607175" duration="20" until="113.0"/> <!-- Nizamuddin Road Bridge -->
        <stop busStop="6362085192" duration="20" until="168.0"/> <!-- Indraprastha Park -->
        <stop busStop="13669726310" duration="20" until="301.0"/> <!-- Sarai Kale Khan -->
    </route>
    <route id="pt_bus_BPExp:1" edges="1491586823 70258954#1 70258954#3 70258954#4 70258954#5 555197204 679512999-AddedOnRampEdge 679512999 679512999-AddedOffRampEdge 679512998 679512997 1313465445 70258948#0 70258948#1 70258948#2" >
        <stop busStop="838835305" duration="20" until="39.0"/> <!-- Sarai Kale Khan -->
        <stop busStop="5121928130" duration="20" until="103.0"/> <!-- Sarai Kale Khan ISBT -->
        <stop busStop="6362085190" duration="20" until="219.0"/> <!-- Indraprastha Park -->
        <stop busStop="6362085189" duration="20" until="279.0"/> <!-- Nizamuddin Road Bridge -->
    </route>
    <route id="pt_bus_Gurgaon_→_Anand_Vihar_ISBT:0" edges="28746245 1457651694 676708027 676708027-AddedOffRampEdge 1451903122 570427347 43359324 565938868#0-AddedOnRampEdge 565938868#0 677074043 1420705472#1 1420705472#2 1420705472#3 1420705472#4 26664728#0 26664728#1 26664728#2 26664728#3 26664728#4 26664728#5 26664728#6 26664728#7 26664728#8 686625277 686625276 732001899#0 565347502 563679829#0 563679829#1-AddedOnRampEdge 563679829#1 563679829#2 44316346" >
        <stop busStop="6112155497" duration="20" until="253.0"/> <!-- Andrews Ganj -->
    </route>
    <flow id="pt_bus_984A:0" type="pt_bus" route="pt_bus_984A:0" begin="3.0" end="3603.0" period="600" line="984A:0" >
        <param key="name" value="984A: Avantika -&gt;"/>
        <param key="completeness" value="0.21"/>
    </flow>
    <flow id="pt_bus_966EX:0" type="pt_bus" route="pt_bus_966EX:0" begin="119.0" end="3719.0" period="600" line="966EX:0" >
        <param key="completeness" value="0.25"/>
    </flow>
    <flow id="pt_bus_479A:0" type="pt_bus" route="pt_bus_479A:0" begin="15.0" end="3615.0" period="600" line="479A:0" >
        <param key="name" value="479A: Wazirpur Depot -&gt; Badarpur Border"/>
        <param key="completeness" value="0.07"/>
    </flow>
    <flow id="pt_bus_BPExp:0" type="pt_bus" route="pt_bus_BPExp:0" begin="160.0" end="3760.0" period="600" line="BPExp:0" >
        <param key="name" value="Bypass Express: Uttam Nagar Terminal → Sarai Kale Khan ISBT"/>
        <param key="completeness" value="0.20"/>
    </flow>
    <flow id="pt_bus_BPExp:1" type="pt_bus" route="pt_bus_BPExp:1" begin="165.0" end="3765.0" period="600" line="BPExp:1" >
        <param key="name" value="Bypass Express: Sarai Kale Khan ISBT → Uttam Nagar Terminal"/>
        <param key="completeness" value="0.44"/>
    </flow>
    <flow id="pt_bus_166:0" type="pt_bus" route="pt_bus_166:0" begin="15.0" end="3615.0" period="600" line="166:0" >
        <param key="name" value="166: Nizamuddin Railway Station -&gt; ?"/>
        <param key="completeness" value="0.35"/>
    </flow>
    <flow id="pt_bus_534:0" type="pt_bus" route="pt_bus_534:0" begin="204.0" end="3804.0" period="600" line="534:0" >
        <param key="name" value="534: Mehrauli -&gt; Anand Vihar ISBT"/>
        <param key="completeness" value="0.13"/>
    </flow>
    <flow id="pt_bus_534A:0" type="pt_bus" route="pt_bus_534A:0" begin="218.0" end="3818.0" period="600" line="534A:0" >
        <param key="name" value="534A: IGI Airport -&gt; Anand Vihar ISBT"/>
        <param key="completeness" value="0.08"/>
    </flow>
    <flow id="pt_bus_578:0" type="pt_bus" route="pt_bus_578:0" begin="222.0" end="3822.0" period="600" line="578:0" >
        <param key="name" value="578: Najafgarh → Safdarjung Terminal"/>
        <param key="completeness" value="0.14"/>
    </flow>
    <flow id="pt_bus_519:0" type="pt_bus" route="pt_bus_519:0" begin="227.0" end="3827.0" period="600" line="519:0" >
        <param key="name" value="519: Mandi Gaon → Safdarjung Terminal"/>
        <param key="completeness" value="0.17"/>
    </flow>
    <flow id="pt_bus_427:0" type="pt_bus" route="pt_bus_427:0" begin="227.0" end="3827.0" period="600" line="427:0" >
        <param key="name" value="427: Nizamuddin Railway Station -&gt; Mehrauli Terminal"/>
        <param key="completeness" value="0.11"/>
    </flow>
    <flow id="pt_bus_410:0" type="pt_bus" route="pt_bus_410:0" begin="237.0" end="3837.0" period="600" line="410:0" >
        <param key="name" value="410: Jal Vihar Terminal -&gt; Khyala JJ Colony"/>
        <param key="completeness" value="0.15"/>
    </flow>
    <flow id="pt_bus_166:1" type="pt_bus" route="pt_bus_166:1" begin="17.0" end="3617.0" period="600" line="166:1" >
        <param key="name" value="166: ? -&gt; Nizamuddin Railway Station"/>
        <param key="completeness" value="0.37"/>
    </flow>
    <flow id="pt_bus_611:0" type="pt_bus" route="pt_bus_611:0" begin="253.0" end="3853.0" period="600" line="611:0" >
        <param key="name" value="611: Dhaula Kuan -&gt; Mayur Vihar Phase 3"/>
        <param key="completeness" value="0.03"/>
    </flow>
    <flow id="pt_bus_727:0" type="pt_bus" route="pt_bus_727:0" begin="275.0" end="3875.0" period="600" line="727:0" >
        <param key="name" value="727: Dwarka Mor Metro Station =&gt; Jawaharlal Nehru Stadium"/>
        <param key="completeness" value="0.04"/>
    </flow>
    <flow id="pt_bus_544:0" type="pt_bus" route="pt_bus_544:0" begin="303.0" end="3903.0" period="600" line="544:0" >
        <param key="name" value="544: RK Puram Sector 1 -&gt; Badarpur Border"/>
        <param key="completeness" value="0.04"/>
    </flow>
    <flow id="pt_bus_469:0" type="pt_bus" route="pt_bus_469:0" begin="321.0" end="3921.0" period="600" line="469:0" >
        <param key="name" value="469: Ambedkar Nagar Terminal -&gt; Anand Vihar ISBT"/>
        <param key="completeness" value="0.16"/>
    </flow>
    <flow id="pt_bus_450:0" type="pt_bus" route="pt_bus_450:0" begin="326.0" end="3926.0" period="600" line="450:0" >
        <param key="name" value="450: Jal Vihar Terminal -&gt; Anand Parvat"/>
        <param key="completeness" value="0.11"/>
    </flow>
    <flow id="pt_bus_413:0" type="pt_bus" route="pt_bus_413:0" begin="331.0" end="3931.0" period="600" line="413:0" >
        <param key="name" value="413: Nizamuddin Railway Station -&gt; Mehrauli Terminal"/>
        <param key="completeness" value="0.14"/>
    </flow>
    <flow id="pt_bus_543:0" type="pt_bus" route="pt_bus_543:0" begin="334.0" end="3934.0" period="600" line="543:0" >
        <param key="name" value="543: -&gt; Anand Vihar ISBT"/>
        <param key="completeness" value="0.27"/>
    </flow>
    <flow id="pt_bus_479:0" type="pt_bus" route="pt_bus_479:0" begin="340.0" end="3940.0" period="600" line="479:0" >
        <param key="name" value="479: Punjabi Bagh -&gt; Badarpur Border"/>
        <param key="completeness" value="0.09"/>
    </flow>
    <flow id="pt_bus_450:1" type="pt_bus" route="pt_bus_450:1" begin="346.0" end="3946.0" period="600" line="450:1" >
        <param key="name" value="450: Anand Parvat -&gt; Jal Vihar Terminal"/>
        <param key="completeness" value="0.36"/>
    </flow>
    <flow id="pt_bus_413:1" type="pt_bus" route="pt_bus_413:1" begin="350.0" end="3950.0" period="600" line="413:1" >
        <param key="name" value="413: Mehrauli Terminal -&gt; Nizamuddin Railway Station"/>
        <param key="completeness" value="0.14"/>
    </flow>
    <flow id="pt_bus_323:0" type="pt_bus" route="pt_bus_323:0" begin="353.0" end="3953.0" period="600" line="323:0" >
        <param key="name" value="323: Dhaula Kuan → Noida Sector 62"/>
        <param key="completeness" value="0.12"/>
    </flow>
    <flow id="pt_bus_(-)_TMS:0" type="pt_bus" route="pt_bus_(-)_TMS:0" begin="362.0" end="3962.0" period="600" line="(-)_TMS:0" >
        <param key="name" value="(-) Teevra Mudrika Service: Punjabi Bagh Terminal"/>
        <param key="completeness" value="0.03"/>
    </flow>
    <flow id="pt_bus_543A:0" type="pt_bus" route="pt_bus_543A:0" begin="368.0" end="3968.0" period="600" line="543A:0" >
        <param key="name" value="543A: Kapashera Border -&gt; Anand Vihar ISBT"/>
        <param key="completeness" value="0.05"/>
    </flow>
    <flow id="pt_bus_427:1" type="pt_bus" route="pt_bus_427:1" begin="371.0" end="3971.0" period="600" line="427:1" >
        <param key="name" value="427: Mehrauli Terminal -&gt; Nizamuddin Railway Station"/>
        <param key="completeness" value="0.09"/>
    </flow>
    <flow id="pt_bus_418A:0" type="pt_bus" route="pt_bus_418A:0" begin="381.0" end="3981.0" period="600" line="418A:0" >
        <param key="name" value="418A: Badarpur Border -&gt; Shahadra Terminal"/>
        <param key="completeness" value="0.08"/>
    </flow>
    <flow id="pt_bus_405:0" type="pt_bus" route="pt_bus_405:0" begin="386.0" end="3986.0" period="600" line="405:0" >
        <param key="name" value="405: Badarpur Border → Old Delhi Railway Station"/>
        <param key="completeness" value="0.10"/>
    </flow>
    <flow id="pt_bus_410:1" type="pt_bus" route="pt_bus_410:1" begin="393.0" end="3993.0" period="600" line="410:1" >
        <param key="name" value="410: Khyala JJ Colony -&gt; Jal Vihar Terminal"/>
        <param key="completeness" value="0.20"/>
    </flow>
    <flow id="pt_bus_347:0" type="pt_bus" route="pt_bus_347:0" begin="27.0" end="3627.0" period="600" line="347:0" >
        <param key="name" value="347: Kashmere Gate -&gt; Noida Sector 34/51"/>
        <param key="completeness" value="0.06"/>
    </flow>
    <flow id="pt_bus_442:0" type="pt_bus" route="pt_bus_442:0" begin="406.0" end="4006.0" period="600" line="442:0" >
        <param key="name" value="442: Azadpur Metro Station =&gt; Nehru Place"/>
        <param key="completeness" value="0.07"/>
    </flow>
    <flow id="pt_bus_724:0" type="pt_bus" route="pt_bus_724:0" begin="412.0" end="4012.0" period="600" line="724:0" >
        <param key="name" value="724: Uttam Nagar Terminal =&gt; Nehru Place Terminal"/>
        <param key="completeness" value="0.07"/>
    </flow>
    <flow id="pt_bus_(-)_OMS:0" type="pt_bus" route="pt_bus_(-)_OMS:0" begin="418.0" end="4018.0" period="600" line="(-)_OMS:0" >
        <param key="name" value="(-) Outer Mudrika Service: Uttam Nagar Terminal"/>
        <param key="completeness" value="0.05"/>
    </flow>
    <flow id="pt_bus_460:0" type="pt_bus" route="pt_bus_460:0" begin="422.0" end="4022.0" period="600" line="460:0" >
        <param key="name" value="460: Badarpur Border -&gt; Minto Road Terminal"/>
        <param key="completeness" value="0.07"/>
    </flow>
    <flow id="pt_bus_181A:0" type="pt_bus" route="pt_bus_181A:0" begin="437.0" end="4037.0" period="600" line="181A:0" >
        <param key="name" value="181A: Jahangirpuri E-Block -&gt; Nizamuddin Railway Station"/>
        <param key="completeness" value="0.23"/>
    </flow>
    <flow id="pt_bus_181A:1" type="pt_bus" route="pt_bus_181A:1" begin="437.0" end="4037.0" period="600" line="181A:1" >
        <param key="name" value="181A: Nizamuddin Railway Station -&gt; Jahangirpuri E-Block"/>
        <param key="completeness" value="0.19"/>
    </flow>
    <flow id="pt_bus_543B:0" type="pt_bus" route="pt_bus_543B:0" begin="441.0" end="4041.0" period="600" line="543B:0" >
        <param key="name" value="543B: IGI Airport -&gt; Anand Vihar ISBT"/>
        <param key="completeness" value="0.07"/>
    </flow>
    <flow id="pt_bus_Gurgaon_→_Anand_Vihar_ISBT:0" type="pt_bus" route="pt_bus_Gurgaon_→_Anand_Vihar_ISBT:0" begin="465.0" end="4065.0" period="600" line="Gurgaon_→_Anand_Vihar_ISBT:0" >
        <param key="name" value="Gurgaon → Anand Vihar ISBT"/>
        <param key="completeness" value="0.02"/>
    </flow>
    <flow id="pt_bus_624A:0" type="pt_bus" route="pt_bus_624A:0" begin="483.0" end="4083.0" period="600" line="624A:0" >
        <param key="name" value="624A: Munirka -&gt; Anand Vihar ISBT"/>
        <param key="completeness" value="0.04"/>
    </flow>
    <flow id="pt_bus_492:0" type="pt_bus" route="pt_bus_492:0" begin="497.0" end="4097.0" period="600" line="492:0" >
        <param key="name" value="492: Nehru Place -&gt; Noida Sector 62"/>
        <param key="completeness" value="0.20"/>
    </flow>
    <flow id="pt_bus_966:0" type="pt_bus" route="pt_bus_966:0" begin="505.0" end="4105.0" period="600" line="966:0" >
        <param key="name" value="966: Nizamuddin Railway Station =&gt; Nangloi"/>
        <param key="completeness" value="1.00"/>
    </flow>
    <flow id="pt_bus_794:0" type="pt_bus" route="pt_bus_794:0" begin="508.0" end="4108.0" period="600" line="794:0" >
        <param key="name" value="794: Nizamuddin Railway Station -&gt; Manglapuri"/>
        <param key="completeness" value="0.32"/>
    </flow>
    <flow id="pt_bus_966:1" type="pt_bus" route="pt_bus_966:1" begin="517.0" end="4117.0" period="600" line="966:1" >
        <param key="name" value="966: Nangloi =&gt; Nizamuddin Railway Station"/>
        <param key="completeness" value="1.00"/>
    </flow>
    <flow id="pt_bus_794:1" type="pt_bus" route="pt_bus_794:1" begin="525.0" end="4125.0" period="600" line="794:1" >
        <param key="name" value="794: Manglapuri -&gt; Nizamuddin Railway Station"/>
        <param key="completeness" value="0.89"/>
    </flow>
    <flow id="pt_bus_(-)_TMS:1" type="pt_bus" route="pt_bus_(-)_TMS:1" begin="535.0" end="4135.0" period="600" line="(-)_TMS:1" >
        <param key="name" value="(-) Teevra Mudrika Service: Lajpat Nagar"/>
        <param key="completeness" value="0.08"/>
    </flow>
    <flow id="pt_bus_405:1" type="pt_bus" route="pt_bus_405:1" begin="548.0" end="4148.0" period="600" line="405:1" >
        <param key="name" value="405: Badarpur Border → Mori Gate Terminal"/>
        <param key="completeness" value="0.15"/>
    </flow>
    <flow id="pt_bus_410A:0" type="pt_bus" route="pt_bus_410A:0" begin="561.0" end="4161.0" period="600" line="410A:0" >
        <param key="name" value="410A: Subhash Nagar Crossing -&gt; Jal Vihar Terminal"/>
        <param key="completeness" value="0.20"/>
    </flow>
    <flow id="pt_bus_410A:1" type="pt_bus" route="pt_bus_410A:1" begin="565.0" end="4165.0" period="600" line="410A:1" >
        <param key="name" value="410A: Jal Vihar Terminal → Subhash Nagar Crossing"/>
        <param key="completeness" value="0.16"/>
    </flow>
    <flow id="pt_bus_311A:0" type="pt_bus" route="pt_bus_311A:0" begin="574.0" end="4174.0" period="600" line="311A:0" >
        <param key="name" value="311A: Ambedkar Nagar Terminal -&gt; Anand Vihar ISBT"/>
        <param key="completeness" value="0.13"/>
    </flow>
    <flow id="pt_bus_623:1" type="pt_bus" route="pt_bus_623:1" begin="583.0" end="4183.0" period="600" line="623:1" >
        <param key="name" value="623: Shahdara Terminal -&gt; Vasant Vihar CPWD"/>
        <param key="completeness" value="0.19"/>
    </flow>
    <flow id="pt_bus_443:0" type="pt_bus" route="pt_bus_443:0" begin="593.0" end="4193.0" period="600" line="443:0" >
        <param key="name" value="443: Shahdara -&gt; Badarpur Border"/>
        <param key="completeness" value="0.06"/>
    </flow>
    <flow id="pt_bus_623:0" type="pt_bus" route="pt_bus_623:0" begin="58.0" end="3658.0" period="600" line="623:0" >
        <param key="name" value="623: Vasant Vihar CPWD -&gt; Shahdara Terminal"/>
        <param key="completeness" value="0.20"/>
    </flow>
</routes>
